{
  "generated_at": "2025-08-30T14:55:00Z",
  "project_ref": "eqdlaagjaikxdrkgvopn",
  "tables": {
    "orgs": [
      {"id":"2327b18c-d8df-4e8b-be0e-63a0f59b0535","name":"Test Print Shop","slug":"test-print-shop","settings":{"theme":"blue"},"created_at":"2025-08-13T16:48:15.523448+00:00","updated_at":"2025-08-13T16:48:15.523448+00:00"},{"id":"2aaf18a2-ab5c-473e-aa52-3f19821b1f16","name":"Another Print Shop","slug":"another-print-shop","settings":{"theme":"green"},"created_at":"2025-08-13T16:48:36.562446+00:00","updated_at":"2025-08-13T16:48:36.562446+00:00"},{"id":"eaaa0e4b-c240-457e-925d-df32a85856c7","name":"Sid Test Company","slug":"sid-test-company","settings":{},"created_at":"2025-08-14T02:20:28.946872+00:00","updated_at":"2025-08-14T02:20:28.946872+00:00"},{"id":"8aa8d71e-fda8-4af4-b381-626589fe2ca7","name":"Malouf Inc","slug":"malouf-inc","settings":{"theme":"blue","created_at":"2025-08-20T15:56:23.246217+00:00","created_by":"11e5f03e-70fb-4929-bd55-3a0fc4345089"},"created_at":"2025-08-20T15:56:23.246217+00:00","updated_at":"2025-08-20T15:56:23.246217+00:00"},{"id":"deecc1a2-4616-462e-a424-8ac495a06a37","name":"jalkfaj","slug":"jalkfaj","settings":{"theme":"blue","created_at":"2025-08-21T02:06:58.394847+00:00","created_by":"5206c298-1145-4fcc-b010-913c7fc49f96"},"created_at":"2025-08-21T02:06:58.394847+00:00","updated_at":"2025-08-21T02:06:58.394847+00:00"},{"id":"e4f78ade-b419-4469-bbd5-6b19de7157a4","name":"My Print Shop","slug":"my-print-shop","settings":{"theme":"blue","created_at":"2025-08-21T02:20:15.881005+00:00","created_by":"eec4d12d-5c5d-4bf1-b658-c9cf395408b7"},"created_at":"2025-08-21T02:20:15.881005+00:00","updated_at":"2025-08-21T02:20:15.881005+00:00"},{"id":"5da75bab-d769-4707-8e5a-3df1707e645f","name":"Johnson Print Solutions","slug":"johnson-print-solutions","settings":{"zip":"903124","city":"Toronto","email":"sidprabaharan@gmail.com","phone":"5551234567","state":"CT","taxId":"48248-3","theme":"blue","address":"123 Business Ave, Suite 100","country":"Canada","logoUrl":"https://eqdlaagjaikxdrkgvopn.supabase.co/storage/v1/object/public/org-logos/orgs/5da75bab-d769-4707-8e5a-3df1707e645f/logo.png","website":"","imprints":{"methods":[{"id":"embroidery_1756142583510","fees":[{"name":"Vectorizing","price":0},{"name":"Set Up","price":0},{"name":"Screens","price":0},{"name":"Colour Separations","price":0},{"name":"Print Sample","price":0}],"label":"Embroidery","method":"embroidery","enabled":true,"maxWidth":0,"maxColors":0,"maxHeight":0,"colorNotes":"","damageRate":0,"maxQuantity":0,"minQuantity":0,"pricingGrid":[{"oneColor":0,"quantity":"12-23","twoColors":0,"threeColors":0,"fourPlusColors":0},{"oneColor":0,"quantity":"24-47","twoColors":0,"threeColors":0,"fourPlusColors":0},{"oneColor":0,"quantity":"48-71","twoColors":0,"threeColors":0,"fourPlusColors":0},{"oneColor":0,"quantity":"72-143","twoColors":0,"threeColors":0,"fourPlusColors":0},{"oneColor":0,"quantity":"144-287","twoColors":0,"threeColors":0,"fourPlusColors":0},{"oneColor":0,"quantity":"288+","twoColors":0,"threeColors":0,"fourPlusColors":0}],"capabilities":{},"extraCharges":[{"name":"Oversized Print","price":0},{"name":"Sleeve Print","price":0},{"name":"Print on Fleece","price":0},{"name":"Water Based Ink","price":0},{"name":"Discharge Ink","price":0},{"name":"Puff Ink","price":0},{"name":"High Density","price":0},{"name":"Glitter","price":0},{"name":"Silicone","price":0},{"name":"Metallic","price":0},{"name":"Shimmer","price":0},{"name":"Foil","price":0},{"name":"Reflective","price":0},{"name":"Glow in the Dark","price":0},{"name":"Flocking","price":0}],"dailyCapacity":0,"logoSizeNotes":"","inkSpecialties":[],"maxSleeveWidth":0,"maxSleeveHeight":0,"turnaroundTimes":[{"days":0,"type":"Standard","extraCharge":0},{"days":0,"type":"Rush 1","extraCharge":0},{"days":0,"type":"Rush 2","extraCharge":0},{"days":0,"type":"Rush 3","extraCharge":0}]}]},"created_at":"2025-08-13T16:58:24.992456+00:00","created_by":"04d0980b-b3cb-4cc3-9260-7beb624ef30b","production":{"equipment":[{"id":"screen_press_1","name":"Manual Screen Press #1","type":"Screen Printing Press","status":"active","capacity":200,"constraints":{"maxColors":6,"maxScreens":8,"supportedSizes":["S","M","L","XL"],"maxImprintWidth":12,"maxImprintHeight":14,"maxQuantityPerRun":1000,"minQuantityPerRun":1,"supportedPlacements":["front_center","back_center"],"supportedGarmentTypes":["tshirt","polo","hoodie"]},"workingHours":{"friday":{"end":"17:00","start":"09:00","enabled":true},"monday":{"end":"17:00","start":"09:00","enabled":true},"sunday":{"end":"17:00","start":"09:00","enabled":false},"tuesday":{"end":"17:00","start":"09:00","enabled":true},"saturday":{"end":"17:00","start":"09:00","enabled":false},"thursday":{"end":"17:00","start":"09:00","enabled":true},"wednesday":{"end":"17:00","start":"09:00","enabled":true}},"stageAssignments":[{"stageIds":["printing","curing"],"decorationMethod":"screenPrinting"}]},{"id":"embroidery_1","name":"Brother 6-Head Embroidery","type":"Embroidery Machine","status":"active","capacity":150,"constraints":{"maxColors":15,"supportedSizes":["S","M","L","XL"],"maxImprintWidth":12,"maxImprintHeight":14,"maxQuantityPerRun":1000,"minQuantityPerRun":1,"supportedPlacements":["front_center","back_center"],"supportedGarmentTypes":["tshirt","polo","hoodie","cap"]},"workingHours":{"friday":{"end":"17:00","start":"09:00","enabled":true},"monday":{"end":"17:00","start":"09:00","enabled":true},"sunday":{"end":"17:00","start":"09:00","enabled":false},"tuesday":{"end":"17:00","start":"09:00","enabled":true},"saturday":{"end":"15:00","start":"09:00","enabled":true},"thursday":{"end":"17:00","start":"09:00","enabled":true},"wednesday":{"end":"17:00","start":"09:00","enabled":true}},"stageAssignments":[{"stageIds":["hooping","embroidering","trimming"],"decorationMethod":"embroidery"}]},{"id":"dtf_printer_1","name":"DTF Printer Station","type":"DTF Printer","status":"active","capacity":100,"constraints":{"supportedSizes":["S","M","L","XL"],"maxImprintWidth":12,"unlimitedColors":true,"maxImprintHeight":14,"maxQuantityPerRun":1000,"minQuantityPerRun":1,"supportedPlacements":["front_center","back_center"],"supportedGarmentTypes":["tshirt","polo","hoodie"]},"workingHours":{"friday":{"end":"17:00","start":"09:00","enabled":true},"monday":{"end":"17:00","start":"09:00","enabled":true},"sunday":{"end":"17:00","start":"09:00","enabled":false},"tuesday":{"end":"17:00","start":"09:00","enabled":true},"saturday":{"end":"17:00","start":"09:00","enabled":false},"thursday":{"end":"17:00","start":"09:00","enabled":true},"wednesday":{"end":"17:00","start":"09:00","enabled":true}},"stageAssignments":[{"stageIds":["printing","powder"],"decorationMethod":"dtf"}]}],"workingHours":{"friday":{"end":"17:00","start":"09:00","enabled":true},"monday":{"end":"18:00","start":"07:00","enabled":true},"sunday":{"end":"17:00","start":"09:00","enabled":false},"tuesday":{"end":"17:00","start":"09:00","enabled":true},"saturday":{"end":"17:00","start":"09:00","enabled":false},"thursday":{"end":"17:00","start":"09:00","enabled":true},"wednesday":{"end":"17:00","start":"09:00","enabled":true}},"decorationMethods":[{"id":"screenPrinting","name":"screenPrinting","label":"Screen Printing","stages":[{"id":"burn_screens","name":"Burn Screens","color":"bg-blue-500","order":1},{"id":"mix_ink","name":"Mix Ink","color":"bg-purple-500","order":2},{"id":"print","name":"Print","color":"bg-green-500","order":3}],"enabled":true},{"id":"embroidery","name":"embroidery","label":"Embroidery","stages":[{"id":"digitizing","name":"Digitizing","color":"bg-blue-500","order":1},{"id":"hooping","name":"Hooping","color":"bg-purple-500","order":2},{"id":"embroidering","name":"Embroidering","color":"bg-green-500","order":3},{"id":"trimming","name":"Trimming","color":"bg-yellow-500","order":4}],"enabled":true},{"id":"dtf","name":"dtf","label":"DTF","stages":[{"id":"printing","name":"Printing","color":"bg-blue-500","order":1},{"id":"powder","name":"Powder Application","color":"bg-purple-500","order":2},{"id":"curing","name":"Curing","color":"bg-orange-500","order":3},{"id":"pressing","name":"Heat Pressing","color":"bg-red-500","order":4}],"enabled":true},{"id":"dtg","name":"dtg","label":"DTG","stages":[{"id":"pretreat","name":"Pretreatment","color":"bg-blue-500","order":1},{"id":"dtg_print","name":"DTG Print","color":"bg-green-500","order":2},{"id":"dtg_cure","name":"DTG Cure","color":"bg-orange-500","order":3}],"enabled":true}]},"automations":{"leads":{"enabled":true,"assignTo":"none","trustMode":"manual","followupDays":3,"confidenceThreshold":0.8},"emails":{"enabled":true,"trustMode":"manual","excludeDomains":[],"businessHoursOnly":false,"confidenceThreshold":0.8},"quotes":{"enabled":true,"behavior":{"maxAutoAmount":"","autoSendWhenAllowed":false,"defaultDepositPercent":50},"trustMode":"manual","confidenceThreshold":0.8},"outsourcing":{"enabled":true,"fallback":{"enabled":true,"toInHouseIfNone":true},"strategy":"method_based","minQuality":4,"maxLeadDays":7,"methodRules":{"dtf":"capacity","dtg":"capacity","embroidery":"capacity","sublimation":"capacity","heat_transfer":"capacity","laser_engraving":"capacity","screen_printing":"capacity"},"autoAssignBest":true},"leadWorkflows":{"rules":[{"id":"rule_new_lead","key":"new_lead_detection","label":"New Lead from Email Detection","actions":2,"enabled":true,"trigger":"new lead detected"},{"id":"rule_auto_reply","key":"auto_reply","label":"Auto-reply to New Lead","actions":2,"enabled":true,"trigger":"lead status change"},{"id":"rule_followup_unresp","key":"followup_unresponsive","label":"Follow-up for Unresponsive Leads","actions":1,"enabled":true,"trigger":"follow up due"},{"id":"rule_auto_quote","key":"auto_create_quote","label":"Auto-create Quote for Qualified Leads","actions":2,"enabled":true,"trigger":"lead status change"},{"id":"rule_quote_followup","key":"quote_sent_followup","label":"Quote Sent Follow-up","actions":2,"enabled":true,"trigger":"quote sent"}],"enabled":true,"globals":{"autoStatus":true,"autoFollowups":true,"emailDetection":true,"businessHoursOnly":false},"trustMode":"manual","confidenceThreshold":0.8},"statusChanges":[{"id":"status_1756146138951","name":"New Email","actions":[{"id":"act_1756146994153","type":"apply_preset_tasks","params":{},"enabled":true}],"enabled":true,"toStatus":"Processing","createdAt":"2025-08-25T18:22:18.951Z"},{"id":"status_1756388532362","name":"Approved","actions":[{"id":"act_1756388532362_create_notification","type":"create_notification","enabled":true},{"id":"act_1756391163177","type":"trigger_webhook","params":{"url":"https://webhook.site/d72562bb-5622-4623-957f-759f7aa8731f","method":"POST","payload":"{}"},"enabled":true},{"id":"act_1756391842476","type":"send_email","params":{"subject":"Ink_IQ","template":"order_confirmation","recipient":"customer"},"enabled":true}],"enabled":true,"toStatus":"Approved","createdAt":"2025-08-28T13:42:12.362Z"}],"webhookSecret":" [Convert]::ToBase64String((New-Object Byte[] 32 | %{$=(Get-Random -Maximum 256)}))","mixedWorkflows":{"sequence":["screen_printing","dtf","dtg","embroidery"],"autoDetect":true,"defaultSupplier":"Primary Supplier","defaultWarehouse":"Main Warehouse","preferExpressBetweenSteps":false},"purchaseOrders":[],"schedulingRules":[{"id":"sched_1756147995664","days":["Mon","Tue","Wed","Thu","Fri"],"name":"onpj","enabled":true,"endHour":"17:00","methods":["embroidery"],"createdAt":"2025-08-25T18:53:15.664Z","startHour":"09:00","priorityFilter":"high","preferredEquipment":[]}]},"companyName":"Stitch & Ink","description":"","orderStatuses":[{"id":1,"name":"New","color":"#3498db","active":true},{"id":2,"name":"Processing","color":"#f39c12","active":true},{"id":3,"name":"Artwork Ready","color":"#27ae60","active":true},{"id":4,"name":"Production","color":"#8e44ad","active":true},{"id":5,"name":"Shipping","color":"#16a085","active":true},{"id":6,"name":"Completed","color":"#2ecc71","active":true},{"id":7,"name":"Cancelled","color":"#e74c3c","active":true},{"id":8,"name":"On Hold","color":"#95a5a6","active":false},{"id":9,"name":"Approved","color":"#db3333","active":true},{"id":10,"name":"QA Review ","active":true,"color":"#b733db"}]},"created_at":"2025-08-13T16:58:24.992456+00:00","updated_at":"2025-08-13T16:58:24.992456+00:00"},{"id":"5023b174-a25d-4936-b068-f43f0564e7f1","name":"Stitch & Ink","slug":"stitch---ink","settings":{"theme":"blue","created_at":"2025-08-28T22:25:16.823712+00:00","created_by":"0eba8307-df27-42bc-bde0-5bc44ad33707","automations":{"leads":{"enabled":true,"assignTo":"none","trustMode":"manual","followupDays":3,"confidenceThreshold":0.8},"emails":{"enabled":true,"trustMode":"manual","excludeDomains":[],"businessHoursOnly":false,"confidenceThreshold":0.8},"quotes":{"enabled":true,"behavior":{"maxAutoAmount":"","autoSendWhenAllowed":false,"defaultDepositPercent":50},"trustMode":"manual","confidenceThreshold":0.8},"outsourcing":{"enabled":true,"fallback":{"enabled":true,"toInHouseIfNone":true},"strategy":"method_based","minQuality":4,"maxLeadDays":7,"methodRules":{"dtf":"capacity","dtg":"capacity","embroidery":"capacity","sublimation":"capacity","heat_transfer":"capacity","laser_engraving":"capacity","screen_printing":"capacity"},"autoAssignBest":true},"leadWorkflows":{"rules":[{"id":"rule_new_lead","key":"new_lead_detection","label":"New Lead from Email Detection","actions":2,"enabled":true,"trigger":"new lead detected"},{"id":"rule_auto_reply","key":"auto_reply","label":"Auto-reply to New Lead","actions":2,"enabled":true,"trigger":"lead status change"},{"id":"rule_followup_unresp","key":"followup_unresponsive","label":"Follow-up for Unresponsive Leads","actions":1,"enabled":true,"trigger":"follow up due"},{"id":"rule_auto_quote","key":"auto_create_quote","label":"Auto-create Quote for Qualified Leads","actions":2,"enabled":true,"trigger":"lead status change"},{"id":"rule_quote_followup","key":"quote_sent_followup","label":"Quote Sent Follow-up","actions":2,"enabled":true,"trigger":"quote sent"}],"enabled":true,"globals":{"autoStatus":true,"autoFollowups":true,"emailDetection":true,"businessHoursOnly":false},"trustMode":"manual","confidenceThreshold":0.8},"statusChanges":[{"id":"status_1756503910697_approved","name":"Approved → Email Customer","actions":[{"type":"send_email","params":{"template":"approval_confirmation","recipient":"customer"}}],"enabled":true,"toStatus":"Approved","createdAt":"2025-08-29T21:45:10.697Z"},{"id":"status_1756503910697_inprod","name":"In Production → Notify Team","actions":[{"type":"create_notification","params":{"message":"Order moved to production"}}],"enabled":true,"toStatus":"In Production","createdAt":"2025-08-29T21:45:10.697Z"},{"id":"status_1756503910697_completed","name":"Complete → Email Customer","actions":[{"type":"send_email","params":{"template":"completion_notice","recipient":"customer"}}],"enabled":true,"toStatus":"Complete","createdAt":"2025-08-29T21:45:10.697Z"}],"mixedWorkflows":{"sequence":["screen_printing","dtf","dtg","embroidery"],"autoDetect":true,"defaultSupplier":"Primary Supplier","defaultWarehouse":"Main Warehouse","preferExpressBetweenSteps":false},"purchaseOrders":[],"schedulingRules":[]}},"created_at":"2025-08-28T22:25:16.823712+00:00","updated_at":"2025-08-28T22:25:16.823712+00:00"}
    ],
    "customers": [
      {"id":"520bb780-faed-4298-b088-733e5909520d","org_id":"5da75bab-d769-4707-8e5a-3df1707e645f","name":"Sid Prabbs","email":"sidtest688@gmail.com","phone":"2898288554","company":"Sid","address":{"zip":"903124","city":"Toronto","state":"CT","street":"123 Business Ave, Suite 100","country":"Canada"},"notes":"Industry: healthcare, Job Title: DJ","status":"active","created_at":"2025-08-15T18:37:00.160334+00:00","updated_at":"2025-08-15T18:37:00.160334+00:00"},{"id":"ef315b3a-6a3c-4d6c-b6a4-97e0d8ff784e","org_id":"eaaa0e4b-c240-457e-925d-df32a85856c7","name":"Sid Prabaharan","email":"21sssp1@gmail.com","phone":"2898288554","company":"Sid","address":{"zip":"903124","city":"Toronto","state":"CT","street":"123 Business Ave, Suite 100","country":"Canada"},"notes":"Industry: retail, Job Title: Nothing","status":"active","created_at":"2025-08-15T18:43:35.377086+00:00","updated_at":"2025-08-15T18:43:35.377086+00:00"},{"id":"a59c85a6-07e5-419b-9e5d-5b48b4bdfc9a","org_id":"e4f78ade-b419-4469-bbd5-6b19de7157a4","name":"Sid Prabbs","email":"sidtest688@gmail.com","phone":"(289) 828-8554","company":"InkIQ","address":{"zip":"903124","city":"Toronto","state":"CT","street":"123 Business Ave, Suite 100","country":"Canada"},"notes":"Industry: retail, Job Title: Job","status":"active","created_at":"2025-08-21T02:36:34.48034+00:00","updated_at":"2025-08-21T02:36:34.48034+00:00"},{"id":"09c1216e-2f85-4961-aed4-d09e2df6e9dc","org_id":"8aa8d71e-fda8-4af4-b381-626589fe2ca7","name":"John Dobson","email":"gleason@gleasons.com","phone":"(514) 555-6696","company":"Gleason's Gym","address":{"zip":"19958","city":"Lewes","state":"Delaware","street":"16192 Coastal Highway","country":"United States"},"notes":"Industry: tech, Job Title: Owner","status":"active","created_at":"2025-08-28T22:34:54.711615+00:00","updated_at":"2025-08-28T22:34:54.711615+00:00"},{"id":"5cc743e7-515e-49f3-b3dd-a760a7bf27fc","org_id":"5023b174-a25d-4936-b068-f43f0564e7f1","name":"John Ballsack","email":"kiriakosp@icloud.com","phone":"(514) 834-6659","company":"Ballsack Inc.","address":{"zip":"H7X 3R9","city":"LAVAL","state":"QUEBEC","street":"226 Rue Du Domaine","country":"Canada"},"notes":"Industry: education, Job Title: Retard","status":"active","created_at":"2025-08-28T22:45:43.592208+00:00","updated_at":"2025-08-28T22:45:43.592208+00:00"}
    ],
    "products": [
      {"id":"d0a0a272-34d1-42ce-8327-4b6f1b5a1112","org_id":"2327b18c-d8df-4e8b-be0e-63a0f59b0535","sku":"BC-PG-001","name":"Business Cards - Premium Glossy","description":"Premium glossy business cards, 350gsm paper, standard 3.5\" x 2\" size","category":"Business Cards","base_price":45,"cost_price":15,"dimensions":"3.5\" x 2\"","materials":"350gsm Premium Glossy","min_quantity":250,"max_quantity":10000,"active":true,"created_at":"2025-08-13T17:26:33.294812+00:00","updated_at":"2025-08-13T17:26:33.294812+00:00"},{"id":"20b3e6f6-c201-4911-bbce-24968552ca22","org_id":"5da75bab-d769-4707-8e5a-3df1707e645f","sku":"BC-PG-002","name":"Business Cards - Matte Finish","description":"Professional matte finish business cards, 350gsm paper","category":"Business Cards","base_price":42,"cost_price":14,"dimensions":"3.5\" x 2\"","materials":"350gsm Matte","min_quantity":250,"max_quantity":10000,"active":true,"created_at":"2025-08-13T17:27:49.001848+00:00","updated_at":"2025-08-13T17:27:49.001848+00:00"}
    ],
    "quotes": [
      {"id":"468e9c5e-c82a-4a2d-8fed-eecc92ddaf90","org_id":"eaaa0e4b-c240-457e-925d-df32a85856c7","customer_id":"ef315b3a-6a3c-4d6c-b6a4-97e0d8ff784e","quote_number":"0001","status":"sent","subject":"New Quotation","description":"Quote created from frontend","total_amount":60,"tax_rate":0.08,"tax_amount":0.05,"discount_percentage":0,"discount_amount":0,"final_amount":60.05,"valid_until":"2025-09-15","sent_date":"2025-08-16T18:21:25.006717+00:00","approved_date":null,"notes":"Quote created via NewQuote component","terms_conditions":"Standard terms apply","created_by":"e8f477e0-cb48-43b7-974d-d3585c28e95d","updated_by":"e8f477e0-cb48-43b7-974d-d3585c28e95d","created_at":"2025-08-16T18:21:15.180933+00:00","updated_at":"2025-08-16T18:21:25.006717+00:00","production_due_date":null,"customer_due_date":null,"payment_due_date":null,"invoice_date":null},
      {"id":"7f6cdd8c-de70-4174-b1b3-c91712a88841","org_id":"eaaa0e4b-c240-457e-925d-df32a85856c7","customer_id":"ef315b3a-6a3c-4d6c-b6a4-97e0d8ff784e","quote_number":"0008","status":"sent","subject":"New Quotation","description":"Quote created from frontend","total_amount":20,"tax_rate":0.08,"tax_amount":0.02,"discount_percentage":0,"discount_amount":0,"final_amount":20.02,"valid_until":"2025-09-17","sent_date":"2025-08-18T15:05:15.166369+00:00","approved_date":null,"notes":"Quote created via NewQuote component","terms_conditions":"Standard terms apply","created_by":"e8f477e0-cb48-43b7-974d-d3585c28e95d","updated_by":"e8f477e0-cb48-43b7-974d-d3585c28e95d","created_at":"2025-08-18T15:05:13.432637+00:00","updated_at":"2025-08-18T15:05:15.166369+00:00","production_due_date":null,"customer_due_date":"2025-08-30","payment_due_date":null,"invoice_date":null}
      ],
    "quote_items": [
      {"id":"033160d5-f193-401f-a096-73a6dcb97eef","quote_id":"468e9c5e-c82a-4a2d-8fed-eecc92ddaf90","org_id":"eaaa0e4b-c240-457e-925d-df32a85856c7","product_name":"Custom T-Shirt","product_sku":"ITEM-001","product_description":"Custom T-Shirt","quantity":1,"unit_price":20,"total_price":20,"imprint_type":"screen-print","setup_fee":0,"imprint_cost":0,"notes":null,"created_at":"2025-08-16T18:21:15.180933+00:00","updated_at":"2025-08-16T18:21:15.180933+00:00","category":"T-Shirts","item_number":"ITEM-001","color":"Black","xs":0,"s":0,"m":1,"l":0,"xl":0,"xxl":0,"xxxl":0,"taxed":true,"garment_status":"pending","mockup_images":null,"group_index":1,"group_label":"Group 1"}
    ],
    "invoices": [
      {"id":"e0d4eadb-a5e7-43f2-8fd6-42d8725a68ce","org_id":"eaaa0e4b-c240-457e-925d-df32a85856c7","quote_id":"2add4209-7674-48d1-90d9-51aa9782097f","customer_id":"ef315b3a-6a3c-4d6c-b6a4-97e0d8ff784e","invoice_number":"INV-2025-00001","status":"draft","invoice_date":"2025-08-18T14:51:51.175644+00:00","due_date":null,"subtotal":20,"tax_amount":0.02,"discount_amount":0,"shipping_amount":0,"total_amount":20.02,"balance_due":20.02,"currency":"USD","notes":null,"terms":null,"created_by":null,"updated_by":null,"created_at":"2025-08-18T14:51:51.175644+00:00","updated_at":"2025-08-18T14:51:51.175644+00:00"}
    ],
    "invoice_items": [
      {"id":"7a2edb4a-0364-44f0-b349-010f73f489d1","invoice_id":"e0d4eadb-a5e7-43f2-8fd6-42d8725a68ce","line_no":1,"item_type":"product","product_name":"Custom T-Shirt","product_sku":"ITEM-001","description":"Custom T-Shirt","category":"T-Shirts","color":"Black","qty":1,"unit_price":20,"line_subtotal":20,"taxed":true,"xs":0,"s":0,"m":1,"l":0,"xl":0,"xxl":0,"xxxl":0,"group_index":1,"group_label":"Group 1","created_at":"2025-08-18T14:51:51.175644+00:00","quote_item_id":null}
    ],
    "profiles": [
      {"id":"04d0980b-b3cb-4cc3-9260-7beb624ef30b","email":"sidprabaharan@gmail.com","full_name":"Sid Prabbs","avatar_url":null,"created_at":"2025-08-13T16:58:24.992456+00:00","updated_at":"2025-08-13T16:58:24.992456+00:00"},{"id":"e8f477e0-cb48-43b7-974d-d3585c28e95d","email":"sidtest688@gmail.com","full_name":"Sid Prabbs","avatar_url":null,"created_at":"2025-08-14T02:20:28.946872+00:00","updated_at":"2025-08-14T02:20:28.946872+00:00"},{"id":"11e5f03e-70fb-4929-bd55-3a0fc4345089","email":"william@maloufco.com","full_name":"William Malouf","avatar_url":null,"created_at":"2025-08-20T15:56:23.246217+00:00","updated_at":"2025-08-20T15:56:23.246217+00:00"},{"id":"5206c298-1145-4fcc-b010-913c7fc49f96","email":"sid@inkiq.io","full_name":"Sid Prabbs","avatar_url":null,"created_at":"2025-08-21T02:06:58.394847+00:00","updated_at":"2025-08-21T02:06:58.394847+00:00"},{"id":"eec4d12d-5c5d-4bf1-b658-c9cf395408b7","email":"21sssp1@gmail.com","full_name":"User","avatar_url":null,"created_at":"2025-08-21T02:20:15.881005+00:00","updated_at":"2025-08-21T02:20:15.881005+00:00"},{"id":"0eba8307-df27-42bc-bde0-5bc44ad33707","email":"kiriakos@stitchandink.ca","full_name":"Kiriakos Primbas","avatar_url":null,"created_at":"2025-08-28T22:25:16.823712+00:00","updated_at":"2025-08-28T22:25:16.823712+00:00"}
    ]
  }
}



